{
  "inputType": "exploratory_workflow",
  "workflowId": "LOGIN_001",
  "workflowName": "Login",
  "module": "Authentication",
  "feature": "Login",
  "applicationCode": "WT",
  "source": {
    "createdBy": "UI user",
    "notes": "Workflow entered from MVP UI."
  },
  "resourceFiles": [
    "login_page/login_page.resource"
  ],
  "pages": [
    {
      "name": "login_page",
      "url": "https://opensource-demo.orangehrmlive.com/web/index.php/auth/login"
    }
  ],
  "observedPreconditions": [
    "Go to login Page: https://opensource-demo.orangehrmlive.com/web/index.php/auth/login",
    "Username, password textbox, login button and forgot password link should be visible on this page",
    "Valid Credentials are:",
    "Username : Admin",
    "Password : admin123"
  ],
  "observedSteps": [],
  "observedExpectedResult": "",
  "fields": [],
  "observedValidations": [
    "User should be able to login with valid credentials",
    "Sign in failed with invalid or incorrect credentials with invalid credential message",
    "Successful login take the user to dashboard page: https://opensource-demo.orangehrmlive.com/web/index.php/dashboard/index",
    "Click on the manda user and then logout button should navigate back to login page"
  ],
  "testData": {},
  "scenarioIntent": [
    "positive",
    "negative",
    "edge",
    "ui"
  ]
}